debug_visuals/__init__.py
debug_visuals/debug_visuals.py
debug_visuals-0.0.3.dist-info/METADATA
debug_visuals-0.0.3.dist-info/WHEEL
debug_visuals-0.0.3.dist-info/top_level.txt
debug_visuals-0.0.3.dist-info/RECORD
