Metadata-Version: 2.1
Name: debug-visuals
Version: 0.0.3
Summary: Visualization functions ready-to-use with VS Code Debug Visualizer
Home-page: UNKNOWN
Author: Fabian Tepe
Author-email: fabiantepe1.2@gmail.com
License: MIT
Platform: UNKNOWN
